{
  "schedules": [
    {
      "id": 1,
      "clientName": "Mariana Silva",
      "service": "Corte feminino",
      "stylist": "Luana",
      "date": "2025-11-10",
      "time": "14:30",
      "status": "confirmado",
      "notes": "Trara foto de referência",
      "createdAt": "2025-11-01T10:00:00-03:00"
    },
    {
      "id": 2,
      "clientName": "Carlos Pereira",
      "service": "Barba e corte",
      "stylist": "Rafael",
      "date": "2025-11-11",
      "time": "09:00",
      "status": "pendente",
      "notes": "",
      "createdAt": "2025-11-02T16:25:00-03:00"
    },
    {
      "id": 3,
      "clientName": "Ana Costa",
      "service": "Coloração",
      "stylist": "Luana",
      "date": "2025-11-12",
      "time": "18:00",
      "status": "confirmado",
      "notes": "Alérgica a amônia — usar produto sem amônia",
      "createdAt": "2025-11-03T09:45:00-03:00"
    }
  ],
  "services": [
    { "id": 1, "name": "Corte feminino", "durationMinutes": 60, "price": 80 },
    { "id": 2, "name": "Corte masculino", "durationMinutes": 40, "price": 50 },
    { "id": 3, "name": "Coloração", "durationMinutes": 120, "price": 200 },
    { "id": 4, "name": "Barba e corte", "durationMinutes": 50, "price": 70 }
  ],
  "stylists": [
    { "id": 1, "name": "Luana", "specialties": ["Corte feminino", "Coloração"] },
    { "id": 2, "name": "Rafael", "specialties": ["Corte masculino", "Barba e corte"] }
  ]
}
